{
    "author": "AlterNET Software",
    "classifications": [ "UI", "GUI", "AlterNET UI", "Cross Platform", "Desktop" ],
    "description": "A project for creating an Alternet UI cross-platform application.",
    "name": "AlterNET UI Application (C#)",
    "identity": "Alternet.UI.Application.CSharp",
    "groupidentity": "Alternet.UI.Application",
    "shortName": "alternet-ui",
    "tags": {
        "language": "C#",
        "type" : "project"
    },
    "sourceName": "Alternet.UI.Templates.Application.CSharp",
    "preferNameDirectory" : "true"
}